veripy/__init__.py
veripy/main.py
veripy_sercurity-1.0.0.dist-info/METADATA
veripy_sercurity-1.0.0.dist-info/WHEEL
veripy_sercurity-1.0.0.dist-info/top_level.txt
veripy_sercurity-1.0.0.dist-info/RECORD
