Metadata-Version: 2.4
Name: veripy-sercurity
Version: 1.0.0
Summary: Email verification system
Author-email: Yixuan Xu <xuyixuan370@gmail.com>
License: MIT
Classifier: License :: OSI Approved :: MIT License
Classifier: Programming Language :: Python :: 3
Classifier: Programming Language :: Python :: 3.11
Requires-Python: >=3.7
Requires-Dist: tk
